{
  "indexes": [
    {
      "collectionGroup": "activationBatches",
      "queryScope": "COLLECTION",
      "fields": [
        {
          "fieldPath": "scenarioId",
          "order": "ASCENDING"
        },
        {
          "fieldPath": "siteId",
          "order": "ASCENDING"
        },
        {
          "fieldPath": "status",
          "order": "ASCENDING"
        },
        {
          "fieldPath": "createdAt",
          "order": "DESCENDING"
        },
        {
          "fieldPath": "__name__",
          "order": "DESCENDING"
        }
      ],
      "density": "SPARSE_ALL"
    }
  ],
  "fieldOverrides": []
}